regi0/__init__.py
regi0/_helpers.py
regi0/readers.py
regi0/verification.py
regi0/writers.py
regi0/cli/__init__.py
regi0/cli/cli.py
regi0/cli/commands/__init__.py
regi0/cli/commands/geographic.py
regi0/cli/commands/setup.py
regi0/cli/commands/taxonomic.py
regi0/cli/config/logger.ini
regi0/cli/config/settings.ini
regi0/cli/utils/__init__.py
regi0/cli/utils/config.py
regi0/cli/utils/logger.py
regi0/geographic/__init__.py
regi0/geographic/duplicates.py
regi0/geographic/local.py
regi0/geographic/outliers.py
regi0/geographic/web/__init__.py
regi0/geographic/web/arcgis.py
regi0/taxonomic/__init__.py
regi0/taxonomic/_helpers.py
regi0/taxonomic/local.py
regi0/taxonomic/parsing.py
regi0/taxonomic/_constants/__init__.py
regi0/taxonomic/_constants/qualifiers.py
regi0/taxonomic/web/__init__.py
regi0/taxonomic/web/gnr.py
regi0/taxonomic/web/iucn.py
regi0/taxonomic/web/speciesplus.py
regi0-0.2.4.dist-info/LICENSE.txt
regi0-0.2.4.dist-info/METADATA
regi0-0.2.4.dist-info/WHEEL
regi0-0.2.4.dist-info/entry_points.txt
regi0-0.2.4.dist-info/top_level.txt
regi0-0.2.4.dist-info/RECORD
