Metadata-Version: 2.1
Name: regi0
Version: 0.2.4
Summary: A Python toolkit to complement and verify biological records.
Home-page: https://github.com/PEM-Humboldt/regi0
Author: Marcelo Villa-Piñeros
Author-email: mvilla@humboldt.org.co
License: UNKNOWN
Platform: UNKNOWN
Classifier: Programming Language :: Python :: 3
Classifier: Programming Language :: Python :: 3.7
Classifier: Programming Language :: Python :: 3.8
Classifier: Programming Language :: Python :: 3.9
Classifier: License :: OSI Approved :: MIT License
Classifier: Operating System :: OS Independent
Requires-Python: <3.10,>=3.7
License-File: LICENSE.txt
Requires-Dist: appdirs
Requires-Dist: click
Requires-Dist: Fiona
Requires-Dist: geopandas (>=0.10)
Requires-Dist: numpy (>=1.15)
Requires-Dist: openpyxl
Requires-Dist: pandas
Requires-Dist: pygeos
Requires-Dist: rapidfuzz
Requires-Dist: rasterio (>=1.2)
Requires-Dist: rasterstats
Requires-Dist: requests
Requires-Dist: scipy
Provides-Extra: dev
Requires-Dist: black ; extra == 'dev'
Requires-Dist: ipython ; extra == 'dev'
Provides-Extra: docs
Requires-Dist: sphinx ; extra == 'docs'
Requires-Dist: sphinx-rtd-theme ; extra == 'docs'
Provides-Extra: test
Requires-Dist: coverage ; extra == 'test'
Requires-Dist: pytest ; extra == 'test'
